metabayes/__init__.py
metabayes/gibbs_sampler.py
metabayes/priors.py
metabayes-0.0.2.dist-info/LICENSE.txt
metabayes-0.0.2.dist-info/METADATA
metabayes-0.0.2.dist-info/WHEEL
metabayes-0.0.2.dist-info/top_level.txt
metabayes-0.0.2.dist-info/RECORD
